sa_tools_core/__init__.py
sa_tools_core/access.py
sa_tools_core/client.py
sa_tools_core/consts.py
sa_tools_core/disk.py
sa_tools_core/dns.py
sa_tools_core/github.py
sa_tools_core/icinga.py
sa_tools_core/notify.py
sa_tools_core/script.py
sa_tools_core/tc.py
sa_tools_core/uptime.py
sa_tools_core/utils.py
sa_tools_core/libs/__init__.py
sa_tools_core/libs/ansible.py
sa_tools_core/libs/editor.py
sa_tools_core/libs/es.py
sa_tools_core/libs/github.py
sa_tools_core/libs/icinga.py
sa_tools_core/libs/ncdu.py
sa_tools_core/libs/notification_gateway.py
sa_tools_core/libs/permission.py
sa_tools_core/libs/process.py
sa_tools_core/libs/sentry.py
sa_tools_core/libs/template.py
sa_tools_core/libs/timeformat.py
sa_tools_core/libs/notify/__init__.py
sa_tools_core/libs/notify/email.py
sa_tools_core/libs/notify/lark.py
sa_tools_core/libs/notify/pushbullet.py
sa_tools_core/libs/notify/pushover.py
sa_tools_core/libs/notify/sms.py
sa_tools_core/libs/notify/telegram.py
sa_tools_core/libs/notify/wework.py
sa_tools_core/templates/icinga/notification.mako
sa_tools_core-0.6.0.dist-info/METADATA
sa_tools_core-0.6.0.dist-info/WHEEL
sa_tools_core-0.6.0.dist-info/entry_points.txt
sa_tools_core-0.6.0.dist-info/top_level.txt
sa_tools_core-0.6.0.dist-info/RECORD
