Metadata-Version: 2.1
Name: sa-tools-core
Version: 0.6.0
Summary: SA Tools Core
Home-page: https://github.com/douban/sa-tools-core
Author: sysadmin
Author-email: sysadmin@douban.com
License: BSD
Keywords: sa-tools,sysadmin,command line tools
Platform: UNKNOWN
Classifier: Programming Language :: Python
Classifier: Programming Language :: Python :: 3
Classifier: Programming Language :: Python :: 3.6
Classifier: Programming Language :: Python :: 3.7
Classifier: Development Status :: 5 - Production/Stable
Classifier: Environment :: Console
Classifier: Intended Audience :: Developers
Classifier: License :: OSI Approved :: BSD License
Classifier: Operating System :: POSIX :: Linux
Classifier: Topic :: Software Development :: Libraries :: Python Modules
Requires-Dist: setuptools
Requires-Dist: six (>=1.12.0)
Requires-Dist: sentry-sdk
Requires-Dist: wechatpy
Requires-Dist: pylark
Requires-Dist: requests
Requires-Dist: pydnspod2
Requires-Dist: elasticsearch (>=7.0.0)
Requires-Dist: humanize
Provides-Extra: icinga
Requires-Dist: Mako ; extra == 'icinga'
Requires-Dist: icinga2py ; extra == 'icinga'
Requires-Dist: inflect ; extra == 'icinga'
Provides-Extra: script
Requires-Dist: ansible (>=2.8) ; extra == 'script'
Requires-Dist: progressbar2 ; extra == 'script'
Requires-Dist: terminaltables ; extra == 'script'
Provides-Extra: tencentcloud
Requires-Dist: tencentcloud-sdk-python ; extra == 'tencentcloud'
Requires-Dist: PyYAML ; extra == 'tencentcloud'
Requires-Dist: inflection ; extra == 'tencentcloud'
